Iroko/Class.py
Iroko/Currency.py
Iroko/Log.py
Iroko/__about__.py
Iroko/__init__.py
Iroko/color.py
Iroko/database.py
Iroko/document.py
Iroko/identifier.py
Iroko/operator.py
Iroko/range.py
Iroko/traceback.py
Iroko/yaml.py
Iroko/Flask/__init__.py
Iroko/Flask/application.py
Iroko/Flask/component.py
Iroko/Flask/View/__init__.py
Iroko/Flask/View/abstract.py
Iroko/Flask/View/template.py
iroko-0.0.2.dist-info/METADATA
iroko-0.0.2.dist-info/WHEEL
iroko-0.0.2.dist-info/RECORD
